setup.cfg
setup.py
quizlight/__init__.py
quizlight/core.py
quizlight/edit.py
quizlight/quiz.py
quizlight/review.py
quizlight.egg-info/PKG-INFO
quizlight.egg-info/SOURCES.txt
quizlight.egg-info/dependency_links.txt
quizlight.egg-info/entry_points.txt
quizlight.egg-info/top_level.txt