Metadata-Version: 1.1
Name: quizlight
Version: 1.1
Summary: A simple, modular terminal-based quiz program
Home-page: https://github.com/dogoncouch/quizlight
Author: Dan Persons
Author-email: dpersonsdev@gmail.com
License: UNKNOWN
Keywords: educational,education,quiz,testing,education-game,education-materials,python3,terminal-based,console-application,learning
Platform: UNKNOWN
Classifier: Development Status :: 5 - Production/Stable
Classifier: Environment :: Console
Classifier: Intended Audience :: Education
Classifier: License :: OSI Approved :: GNU Lesser General Public License v2 or later (LGPLv2+)
Classifier: Natural Language :: English
Classifier: Operating System :: POSIX
Classifier: Programming Language :: Python :: 3
Classifier: Topic :: Education :: Testing
